{
    "pilot": [
        {
            "_id": "pilot.0000", 
            "callbackhistory": [
                {
                    "state": "Launching", 
                    "timestamp": 1435585299.053
                }, 
                {
                    "state": "PendingActive", 
                    "timestamp": 1435585320.113
                }, 
                {
                    "state": "Active", 
                    "timestamp": 1435585653.934
                }, 
                {
                    "state": "Canceled", 
                    "timestamp": 1435585663.958
                }
            ], 
            "commands": [], 
            "cores_per_node": 16, 
            "description": {
                "_config": {
                    "blowup_factor": {
                        "Agent": 1, 
                        "ExecWatcher": 1, 
                        "ExecWorker": 1, 
                        "Scheduler": 1, 
                        "StageinWorker": 1, 
                        "StageoutWorker": 1, 
                        "UpdateWorker": 1, 
                        "execution_queue": 1, 
                        "schedule_queue": 1, 
                        "stagein_queue": 1, 
                        "stageout_queue": 1, 
                        "update_queue": 1024, 
                        "watch_queue": 1
                    }, 
                    "drop_clones": {
                        "Agent": 1, 
                        "ExecWatcher": 1, 
                        "ExecWorker": 1, 
                        "Scheduler": 1, 
                        "StageinWorker": 1, 
                        "StageoutWorker": 1, 
                        "UpdateWorker": 1, 
                        "execution_queue": 1, 
                        "schedule_queue": 1, 
                        "stagein_queue": 1, 
                        "stageout_queue": 1, 
                        "update_queue": 1, 
                        "watch_queue": 1
                    }, 
                    "number_of_workers": {
                        "ExecWorker": 4, 
                        "StageinWorker": 4, 
                        "StageoutWorker": 4, 
                        "UpdateWorker": 4
                    }
                }, 
                "_iterpos": 0, 
                "access_schema": null, 
                "cleanup": false, 
                "cores": 1024, 
                "memory": null, 
                "project": "TG-MCB090174", 
                "queue": "normal", 
                "resource": "xsede.stampede", 
                "runtime": 30, 
                "sandbox": null
            }, 
            "finished": 1435585663.204, 
            "global_sandbox": "/work/01083/tg803521/radical.pilot.sandbox", 
            "heartbeat": null, 
            "input_transfer_finished": null, 
            "input_transfer_started": null, 
            "log": [
                {
                    "message": "Using bootstrapper /home/merzky/ve/lib/python2.7/site-packages/radical/pilot/bootstrapper/default_bootstrapper.sh", 
                    "timestamp": 1435585298.052
                }, 
                {
                    "message": "Copying bootstrapper 'file://localhost//home/merzky/ve/lib/python2.7/site-packages/radical/pilot/bootstrapper/default_bootstrapper.sh' to agent sandbox (sftp://stampede.tacc.utexas.edu/work/01083/tg803521/radical.pilot.sandbox/rp.session.ip-10-184-31-85.merzky.016615.0082-pilot.0000//pilot_bootstrapper.sh).", 
                    "timestamp": 1435585298.053
                }, 
                {
                    "message": "Copying sdist 'file://localhost//home/merzky/ve/local/lib/python2.7/site-packages/radical/utils/radical.utils-0.28.tar.gz' to sdist sandbox (sftp://stampede.tacc.utexas.edu/work/01083/tg803521/radical.pilot.sandbox/rp.session.ip-10-184-31-85.merzky.016615.0082-pilot.0000/).", 
                    "timestamp": 1435585302.811
                }, 
                {
                    "message": "Copying sdist 'file://localhost//home/merzky/ve/local/lib/python2.7/site-packages/saga/saga-python-v0.28-16-gd61cef7-devel.tar.gz' to sdist sandbox (sftp://stampede.tacc.utexas.edu/work/01083/tg803521/radical.pilot.sandbox/rp.session.ip-10-184-31-85.merzky.016615.0082-pilot.0000/).", 
                    "timestamp": 1435585303.554
                }, 
                {
                    "message": "Copying sdist 'file://localhost//home/merzky/ve/local/lib/python2.7/site-packages/radical/pilot/controller/..//radical.pilot-v0.33-145-g688f18c-test-tmp-exec-dir.tar.gz' to sdist sandbox (sftp://stampede.tacc.utexas.edu/work/01083/tg803521/radical.pilot.sandbox/rp.session.ip-10-184-31-85.merzky.016615.0082-pilot.0000/).", 
                    "timestamp": 1435585305.553
                }, 
                {
                    "message": "Submitting SAGA job with description: {'Project': 'TG-MCB090174', 'Executable': '/bin/bash', 'TotalPhysicalMemory': None, 'WorkingDirectory': '/work/01083/tg803521/radical.pilot.sandbox/rp.session.ip-10-184-31-85.merzky.016615.0082-pilot.0000/', 'Queue': 'normal', 'Environment': {'RADICAL_PILOT_PROFILE': 'TRUE'}, 'WallTimeLimit': 30, 'Arguments': ['-l pilot_bootstrapper.sh', \" -b 'radical.utils-0.28.tar.gz:saga-python-v0.28-16-gd61cef7-devel.tar.gz:radical.pilot-v0.33-145-g688f18c-test-tmp-exec-dir.tar.gz' -c '1024' -d '10' -g '/work/01083/tg803521/radical.pilot.sandbox/ve_stampede_experiments' -j 'SSH' -k 'MPIRUN_RSH' -l 'SLURM' -m '54.221.194.147:24242' -n 'am_experiments' -o 'POPEN' -p 'pilot.0000' -q 'CONTINUOUS' -r '30' -s 'rp.session.ip-10-184-31-85.merzky.016615.0082' -t 'multicore' -u 'create' -v 'local' -e 'module purge' -e 'module load TACC' -e 'module load cluster' -e 'module load Linux' -e 'module load mvapich2' -e 'module load python' -e 'module unload xalt' -e 'export TACC_DELETE_FILES=TRUE'\"], 'Error': 'agent.err', 'Output': 'agent.out', 'TotalCPUCount': 1024}", 
                    "timestamp": 1435585310.123
                }, 
                {
                    "message": "SAGA job submitted with job id [slurm+ssh://stampede.tacc.utexas.edu/]-[5452603]", 
                    "timestamp": 1435585319.519
                }, 
                {
                    "message": "CANCEL received. Terminating.", 
                    "timestamp": 1435585663.204
                }, 
                {
                    "message": "real 35.225663 sec | user 0.979 sec | system 0.743 sec | mem 44924.00 kB", 
                    "timestamp": 1435585663.204
                }
            ], 
            "logfile": "[... CONTENT SHORTENED ...]\n-------|----------------|----------------|----------------|----------------|----------------|----------------|----------------|----------------|----------------|----------------|----------------|----------------|----------------|----------------|----------------|----------------|----------------|----------------|----------------|----------------|----------------|----------------|----------------|----------------|----------------|----------------|----------------|----------------|----------------|'}\n2015-06-29 08:47:34,957 - radical.pilot.agent - DEBUG - bulk update result: {'nModified': 3, 'nUpserted': 0, 'nMatched': 3, 'writeErrors': [], 'upserted': [], 'writeConcernErrors': [], 'nRemoved': 0, 'nInserted': 0}\n2015-06-29 08:47:35,172 - radical.pilot.agent - DEBUG - bulk update result: {'nModified': 1, 'nUpserted': 0, 'nMatched': 1, 'writeErrors': [], 'upserted': [], 'writeConcernErrors': [], 'nRemoved': 0, 'nInserted': 0}\n2015-06-29 08:47:43,204 - radical.pilot.agent - WARNING - CANCEL received. Terminating.\n", 
            "nodes": [
                "c401-403", 
                "c401-703", 
                "c402-001", 
                "c402-101", 
                "c402-103", 
                "c402-201", 
                "c402-401", 
                "c402-502", 
                "c404-504", 
                "c410-701", 
                "c410-702", 
                "c411-803", 
                "c412-004", 
                "c412-704", 
                "c413-604", 
                "c416-601", 
                "c417-502", 
                "c418-702", 
                "c421-702", 
                "c422-304", 
                "c422-602", 
                "c424-102", 
                "c424-503", 
                "c424-504", 
                "c428-401", 
                "c446-801", 
                "c446-803", 
                "c446-804", 
                "c446-901", 
                "c447-104", 
                "c447-202", 
                "c449-004", 
                "c449-102", 
                "c449-902", 
                "c450-104", 
                "c450-201", 
                "c450-202", 
                "c452-401", 
                "c452-402", 
                "c452-801", 
                "c453-202", 
                "c453-203", 
                "c454-102", 
                "c455-504", 
                "c455-904", 
                "c457-102", 
                "c457-401", 
                "c458-204", 
                "c462-203", 
                "c462-204", 
                "c464-001", 
                "c464-002", 
                "c464-003", 
                "c466-801", 
                "c469-503", 
                "c471-203", 
                "c471-204", 
                "c473-402", 
                "c473-403", 
                "c473-404", 
                "c474-303", 
                "c474-304", 
                "c474-803", 
                "c474-804"
            ], 
            "output_transfer_finished": null, 
            "output_transfer_started": null, 
            "pilotmanager": "55914b0f23769c6c023d5421", 
            "saga_job_id": "[slurm+ssh://stampede.tacc.utexas.edu/]-[5452603]", 
            "sagajobid": null, 
            "sandbox": "sftp://stampede.tacc.utexas.edu/work/01083/tg803521/radical.pilot.sandbox/rp.session.ip-10-184-31-85.merzky.016615.0082-pilot.0000/", 
            "started": 1435585653.103, 
            "state": "Canceled", 
            "statehistory": [
                {
                    "state": "PendingLaunch", 
                    "timestamp": 1435585297.423
                }, 
                {
                    "state": "Launching", 
                    "timestamp": 1435585298.05
                }, 
                {
                    "state": "PendingActive", 
                    "timestamp": 1435585319.519
                }, 
                {
                    "state": "Active", 
                    "timestamp": 1435585653.103
                }, 
                {
                    "state": "Canceled", 
                    "timestamp": 1435585663.204
                }
            ], 
            "stderr": "[... CONTENT SHORTENED ...]\n------------|----------------|----------------|----------------|----------------|----------------|----------------|----------------|----------------|----------------|----------------|----------------|----------------|----------------|----------------|----------------|----------------|----------------|----------------|----------------|----------------|----------------|----------------|----------------|----------------|----------------|'}\n2015:06:29 08:47:34 80372  UpdateWorker-2 radical.pilot.agent   : [DEBUG   ] bulk update result: {'nModified': 3, 'nUpserted': 0, 'nMatched': 3, 'writeErrors': [], 'upserted': [], 'writeConcernErrors': [], 'nRemoved': 0, 'nInserted': 0}\n2015:06:29 08:47:35 80372  UpdateWorker-0 radical.pilot.agent   : [DEBUG   ] bulk update result: {'nModified': 1, 'nUpserted': 0, 'nMatched': 1, 'writeErrors': [], 'upserted': [], 'writeConcernErrors': [], 'nRemoved': 0, 'nInserted': 0}\n2015:06:29 08:47:43 80372  HeartbeatMonitor radical.pilot.agent   : [WARNING ] CANCEL received. Terminating.\n", 
            "stdout": "[... CONTENT SHORTENED ...]\ntg803521/radical.pilot.sandbox/ve_stampede_experiments/lib/python2.7/lib-old', '/work/01083/tg803521/radical.pilot.sandbox/ve_stampede_experiments/lib/python2.7/lib-dynload', '/opt/apps/intel13/python/2.7.9/lib/python2.7', '/opt/apps/intel13/python/2.7.9/lib/python2.7/plat-linux2', '/opt/apps/intel13/python/2.7.9/lib/python2.7/lib-tk']\npython: 2.7.9 (default, Apr 26 2015, 12:52:46) \n[GCC Intel(R) C++ gcc 4.4 mode]\nutils : 0.28  : /work/01083/tg803521/radical.pilot.sandbox/ve_stampede_experiments/rp_install/lib/python2.7/site-packages/radical/utils/__init__.pyc\nsaga  : v0.28-16-gd61cef7@devel : /work/01083/tg803521/radical.pilot.sandbox/ve_stampede_experiments/rp_install/lib/python2.7/site-packages/saga/__init__.pyc\npilot : v0.33-145-g688f18c@test-tmp_exec_dir : /work/01083/tg803521/radical.pilot.sandbox/ve_stampede_experiments/rp_install/lib/python2.7/site-packages/radical/pilot/__init__.pyc\n        type  : multicore\n        gitid : $Id$\n\n---------------------------------------------------------------------\n\n", 
            "submitted": 1435585297.424, 
            "unit_ids": [
                "unit.000000"
            ], 
            "unitmanager": "55914b1123769c6c023d5422"
        }
    ], 
    "pmgr": [
        {
            "_id": "55914b0f23769c6c023d5421", 
            "data": {}, 
            "pilot_launcher_workers": 1
        }
    ], 
    "session": {
        "_id": "rp.session.ip-10-184-31-85.merzky.016615.0082", 
        "connected": 1435585295.023, 
        "created": 1435585295.023, 
        "name": "rp.session.ip-10-184-31-85.merzky.016615.0082"
    }, 
    "umgr": [
        {
            "_id": "55914b1123769c6c023d5422", 
            "input_transfer_workers": 2, 
            "output_transfer_workers": 2, 
            "scheduler": "round_robin"
        }
    ], 
    "unit": [
        {
            "Agent_Input_Directives": [], 
            "Agent_Input_Status": null, 
            "Agent_Output_Directives": [], 
            "Agent_Output_Status": null, 
            "FTW_Input_Directives": [
                {
                    "action": "Transfer", 
                    "flags": [
                        "CreateParents", 
                        "SkipFailed"
                    ], 
                    "priority": 0, 
                    "source": "/tmp/input_1K.dat", 
                    "state": "Done", 
                    "target": "input_1K.dat"
                }
            ], 
            "FTW_Input_Status": "Done", 
            "FTW_Output_Directives": [
                {
                    "action": "Transfer", 
                    "flags": [
                        "CreateParents", 
                        "SkipFailed"
                    ], 
                    "priority": 0, 
                    "source": "input_1K.dat", 
                    "state": "Done", 
                    "target": "input_1K.dat"
                }
            ], 
            "FTW_Output_Status": "Done", 
            "_id": "unit.000000", 
            "callbackhistory": [
                {
                    "state": "StagingInput", 
                    "timestamp": 1435585298.455
                }, 
                {
                    "state": "PendingExecution", 
                    "timestamp": 1435585306.477
                }, 
                {
                    "state": "Allocating", 
                    "timestamp": 1435585653.358
                }, 
                {
                    "state": "StagingOutput", 
                    "timestamp": 1435585655.364
                }, 
                {
                    "state": "Done", 
                    "timestamp": 1435585656.367
                }
            ], 
            "description": {
                "arguments": [
                    "0"
                ], 
                "cleanup": false, 
                "cores": 1, 
                "environment": null, 
                "executable": "/bin/sleep", 
                "input_staging": [
                    {
                        "action": "Transfer", 
                        "flags": [
                            "CreateParents", 
                            "SkipFailed"
                        ], 
                        "priority": 0, 
                        "source": "/tmp/input_1K.dat", 
                        "target": "input_1K.dat"
                    }
                ], 
                "kernel": null, 
                "mpi": false, 
                "name": null, 
                "output_staging": [
                    {
                        "action": "Transfer", 
                        "flags": [
                            "CreateParents", 
                            "SkipFailed"
                        ], 
                        "priority": 0, 
                        "source": "input_1K.dat", 
                        "target": "input_1K.dat"
                    }
                ], 
                "post_exec": null, 
                "pre_exec": null, 
                "restartable": false, 
                "stderr": null, 
                "stdout": null
            }, 
            "exec_locs": null, 
            "exit_code": 0, 
            "finished": 1435585653.632, 
            "log": [
                {
                    "message": "Scheduled for data transfer to ComputePilot pilot.0000.", 
                    "timestamp": 1435585297.467
                }, 
                {
                    "message": "Transferring input file file://localhost//tmp/input_1K.dat -> sftp://stampede.tacc.utexas.edu/work/01083/tg803521/radical.pilot.sandbox/rp.session.ip-10-184-31-85.merzky.016615.0082-pilot.0000//unit.000000/input_1K.dat", 
                    "timestamp": 1435585304.712
                }, 
                {
                    "message": "All FTW Input Staging Directives done - 1.", 
                    "timestamp": 1435585305.483
                }, 
                {
                    "message": "unit execution start", 
                    "timestamp": 1435585653.487
                }, 
                {
                    "message": "unit needs no input staging", 
                    "timestamp": 1435585653.378
                }, 
                {
                    "message": "FTW output staging needed", 
                    "timestamp": 1435585653.711
                }, 
                {
                    "message": "Starting transfer of input_1K.dat", 
                    "timestamp": 1435585655.037
                }, 
                {
                    "message": "unit execution completed", 
                    "timestamp": 1435585653.632
                }, 
                {
                    "message": "Transferring output file sftp://stampede.tacc.utexas.edu/work/01083/tg803521/radical.pilot.sandbox/rp.session.ip-10-184-31-85.merzky.016615.0082-pilot.0000//unit.000000/input_1K.dat -> file://localhost/experiments/merzky/rp-paper-2015-micro/input_1K.dat", 
                    "timestamp": 1435585655.925
                }, 
                {
                    "message": "All FTW output staging directives done - 1.", 
                    "timestamp": 1435585655.928
                }
            ], 
            "pilot": "pilot.0000", 
            "pilot_sandbox": "sftp://stampede.tacc.utexas.edu/work/01083/tg803521/radical.pilot.sandbox/rp.session.ip-10-184-31-85.merzky.016615.0082-pilot.0000/", 
            "restartable": false, 
            "sandbox": "sftp://stampede.tacc.utexas.edu/work/01083/tg803521/radical.pilot.sandbox/rp.session.ip-10-184-31-85.merzky.016615.0082-pilot.0000//unit.000000", 
            "slots": [
                "c401-403:0"
            ], 
            "started": 1435585653.487, 
            "state": "Done", 
            "statehistory": [
                {
                    "state": "Scheduling", 
                    "timestamp": 1435585297.46
                }, 
                {
                    "state": "StagingInput", 
                    "timestamp": 1435585298.44
                }, 
                {
                    "state": "PendingExecution", 
                    "timestamp": 1435585305.484
                }, 
                {
                    "state": "Allocating", 
                    "timestamp": 1435585653.285
                }, 
                {
                    "state": "Executing", 
                    "timestamp": 1435585653.487
                }, 
                {
                    "state": "Allocating", 
                    "timestamp": 1435585653.378
                }, 
                {
                    "state": "StagingOutput", 
                    "timestamp": 1435585655.034
                }, 
                {
                    "state": "StagingOutput", 
                    "timestamp": 1435585653.632
                }, 
                {
                    "state": "Done", 
                    "timestamp": 1435585655.929
                }
            ], 
            "stderr": "", 
            "stdout": "", 
            "submitted": 1435585297.462, 
            "unitmanager": "55914b1123769c6c023d5422"
        }
    ]
}