{
    "pilot": [
        {
            "_id": "pilot.0000", 
            "callbackhistory": [
                {
                    "state": "Launching", 
                    "timestamp": 1435345583.241
                }, 
                {
                    "state": "PendingActive", 
                    "timestamp": 1435345625.343
                }, 
                {
                    "state": "Active", 
                    "timestamp": 1435345712.581
                }, 
                {
                    "state": "Canceled", 
                    "timestamp": 1435345722.625
                }
            ], 
            "commands": [], 
            "cores_per_node": 16, 
            "description": {
                "_config": {
                    "blowup_factor": {
                        "Agent": 1, 
                        "ExecWatcher": 1, 
                        "ExecWorker": 1, 
                        "Scheduler": 1, 
                        "StageinWorker": 1, 
                        "StageoutWorker": 1, 
                        "UpdateWorker": 1, 
                        "execution_queue": 128, 
                        "schedule_queue": 1, 
                        "stagein_queue": 1, 
                        "stageout_queue": 1, 
                        "update_queue": 1, 
                        "watch_queue": 1
                    }, 
                    "drop_clones": {
                        "Agent": 1, 
                        "ExecWatcher": 1, 
                        "ExecWorker": 1, 
                        "Scheduler": 1, 
                        "StageinWorker": 1, 
                        "StageoutWorker": 1, 
                        "UpdateWorker": 1, 
                        "execution_queue": 1, 
                        "schedule_queue": 1, 
                        "stagein_queue": 1, 
                        "stageout_queue": 1, 
                        "update_queue": 1, 
                        "watch_queue": 1
                    }, 
                    "number_of_workers": {
                        "ExecWorker": 1, 
                        "StageinWorker": 1, 
                        "StageoutWorker": 1, 
                        "UpdateWorker": 1
                    }
                }, 
                "_iterpos": 0, 
                "access_schema": null, 
                "cleanup": false, 
                "cores": 128, 
                "memory": null, 
                "project": "TG-MCB090174", 
                "queue": "development", 
                "resource": "xsede.stampede", 
                "runtime": 30, 
                "sandbox": null
            }, 
            "finished": 1435345722.369, 
            "global_sandbox": "/work/01083/tg803521/radical.pilot.sandbox", 
            "heartbeat": null, 
            "input_transfer_finished": null, 
            "input_transfer_started": null, 
            "log": [
                {
                    "message": "Using bootstrapper /home/merzky/ve/lib/python2.7/site-packages/radical/pilot/bootstrapper/default_bootstrapper.sh", 
                    "timestamp": 1435345582.239
                }, 
                {
                    "message": "Copying bootstrapper 'file://localhost//home/merzky/ve/lib/python2.7/site-packages/radical/pilot/bootstrapper/default_bootstrapper.sh' to agent sandbox (sftp://stampede.tacc.utexas.edu/work/01083/tg803521/radical.pilot.sandbox/rp.session.ip-10-184-31-85.merzky.016612.0019-pilot.0000//pilot_bootstrapper.sh).", 
                    "timestamp": 1435345582.239
                }, 
                {
                    "message": "Copying sdist 'file://localhost//home/merzky/ve/local/lib/python2.7/site-packages/radical/utils/radical.utils-0.28.tar.gz' to sdist sandbox (sftp://stampede.tacc.utexas.edu/work/01083/tg803521/radical.pilot.sandbox/rp.session.ip-10-184-31-85.merzky.016612.0019-pilot.0000/).", 
                    "timestamp": 1435345589.456
                }, 
                {
                    "message": "Copying sdist 'file://localhost//home/merzky/ve/local/lib/python2.7/site-packages/saga/saga-python-v0.28-16-gd61cef7-devel.tar.gz' to sdist sandbox (sftp://stampede.tacc.utexas.edu/work/01083/tg803521/radical.pilot.sandbox/rp.session.ip-10-184-31-85.merzky.016612.0019-pilot.0000/).", 
                    "timestamp": 1435345591.51
                }, 
                {
                    "message": "Copying sdist 'file://localhost//home/merzky/ve/local/lib/python2.7/site-packages/radical/pilot/controller/..//radical.pilot-v0.33-145-g688f18c-test-tmp-exec-dir.tar.gz' to sdist sandbox (sftp://stampede.tacc.utexas.edu/work/01083/tg803521/radical.pilot.sandbox/rp.session.ip-10-184-31-85.merzky.016612.0019-pilot.0000/).", 
                    "timestamp": 1435345592.725
                }, 
                {
                    "message": "Submitting SAGA job with description: {'Project': 'TG-MCB090174', 'Executable': '/bin/bash', 'TotalPhysicalMemory': None, 'WorkingDirectory': '/work/01083/tg803521/radical.pilot.sandbox/rp.session.ip-10-184-31-85.merzky.016612.0019-pilot.0000/', 'Queue': 'development', 'Environment': {'RADICAL_PILOT_PROFILE': 'TRUE'}, 'WallTimeLimit': 30, 'Arguments': ['-l pilot_bootstrapper.sh', \" -b 'radical.utils-0.28.tar.gz:saga-python-v0.28-16-gd61cef7-devel.tar.gz:radical.pilot-v0.33-145-g688f18c-test-tmp-exec-dir.tar.gz' -c '128' -d '10' -g '/work/01083/tg803521/radical.pilot.sandbox/ve_stampede_experiments' -j 'SSH' -k 'MPIRUN_RSH' -l 'SLURM' -m '54.221.194.147:24242' -n 'am_experiments' -o 'POPEN' -p 'pilot.0000' -q 'CONTINUOUS' -r '30' -s 'rp.session.ip-10-184-31-85.merzky.016612.0019' -t 'multicore' -u 'create' -v 'local' -e 'module purge' -e 'module load TACC' -e 'module load cluster' -e 'module load Linux' -e 'module load mvapich2' -e 'module load python' -e 'module unload xalt' -e 'export TACC_DELETE_FILES=TRUE'\"], 'Error': 'agent.err', 'Output': 'agent.out', 'TotalCPUCount': 128}", 
                    "timestamp": 1435345597.601
                }, 
                {
                    "message": "SAGA job submitted with job id [slurm+ssh://stampede.tacc.utexas.edu/]-[5445649]", 
                    "timestamp": 1435345625.238
                }, 
                {
                    "message": "CANCEL received. Terminating.", 
                    "timestamp": 1435345722.203
                }, 
                {
                    "message": "real 35.225297 sec | user 0.469 sec | system 0.315 sec | mem 44300.00 kB", 
                    "timestamp": 1435345722.203
                }, 
                {
                    "message": "Terminated (_terminate set).", 
                    "timestamp": 1435345722.369
                }, 
                {
                    "message": "real 35.371487 sec | user 0.550 sec | system 0.361 sec | mem 49380.00 kB", 
                    "timestamp": 1435345722.369
                }
            ], 
            "logfile": "[... CONTENT SHORTENED ...]\n--|----------------|'}\n2015-06-26 14:08:32,512 - radical.pilot.agent - INFO - slot status before reschedule: {'timestamp': datetime.datetime(2015, 6, 26, 19, 8, 32, 512329), 'slotstate': '|----------------|----------------|----------------|----------------|----------------|----------------|----------------|----------------|'}\n2015-06-26 14:08:32,512 - radical.pilot.agent - INFO - slot status after  reschedule: {'timestamp': datetime.datetime(2015, 6, 26, 19, 8, 32, 512623), 'slotstate': '|----------------|----------------|----------------|----------------|----------------|----------------|----------------|----------------|'}\n2015-06-26 14:08:33,453 - radical.pilot.agent - DEBUG - bulk update result: {'nModified': 4, 'nUpserted': 0, 'nMatched': 4, 'writeErrors': [], 'upserted': [], 'writeConcernErrors': [], 'nRemoved': 0, 'nInserted': 0}\n2015-06-26 14:08:42,202 - radical.pilot.agent - WARNING - CANCEL received. Terminating.\n2015-06-26 14:08:42,368 - radical.pilot.agent - WARNING - Terminated (_terminate set).\n", 
            "nodes": [
                "c560-401", 
                "c560-402", 
                "c560-403", 
                "c560-404", 
                "c560-501", 
                "c560-502", 
                "c560-503", 
                "c560-504"
            ], 
            "output_transfer_finished": null, 
            "output_transfer_started": null, 
            "pilotmanager": "558da2ab23769c03ca887b47", 
            "saga_job_id": "[slurm+ssh://stampede.tacc.utexas.edu/]-[5445649]", 
            "sagajobid": null, 
            "sandbox": "sftp://stampede.tacc.utexas.edu/work/01083/tg803521/radical.pilot.sandbox/rp.session.ip-10-184-31-85.merzky.016612.0019-pilot.0000/", 
            "started": 1435345712.102, 
            "state": "Canceled", 
            "statehistory": [
                {
                    "state": "PendingLaunch", 
                    "timestamp": 1435345582.225
                }, 
                {
                    "state": "Launching", 
                    "timestamp": 1435345582.236
                }, 
                {
                    "state": "PendingActive", 
                    "timestamp": 1435345625.238
                }, 
                {
                    "state": "Active", 
                    "timestamp": 1435345712.102
                }, 
                {
                    "state": "Canceled", 
                    "timestamp": 1435345722.203
                }, 
                {
                    "state": "Canceled", 
                    "timestamp": 1435345722.369
                }
            ], 
            "stderr": "[... CONTENT SHORTENED ...]\nlot status before reschedule: {'timestamp': datetime.datetime(2015, 6, 26, 19, 8, 32, 512329), 'slotstate': '|----------------|----------------|----------------|----------------|----------------|----------------|----------------|----------------|'}\n2015:06:26 14:08:32 20974  CONTINUOUS   radical.pilot.agent   : [INFO    ] slot status after  reschedule: {'timestamp': datetime.datetime(2015, 6, 26, 19, 8, 32, 512623), 'slotstate': '|----------------|----------------|----------------|----------------|----------------|----------------|----------------|----------------|'}\n2015:06:26 14:08:33 20974  UpdateWorker-0 radical.pilot.agent   : [DEBUG   ] bulk update result: {'nModified': 4, 'nUpserted': 0, 'nMatched': 4, 'writeErrors': [], 'upserted': [], 'writeConcernErrors': [], 'nRemoved': 0, 'nInserted': 0}\n2015:06:26 14:08:42 20974  HeartbeatMonitor radical.pilot.agent   : [WARNING ] CANCEL received. Terminating.\n2015:06:26 14:08:42 20974  MainThread   radical.pilot.agent   : [WARNING ] Terminated (_terminate set).\n", 
            "stdout": "[... CONTENT SHORTENED ...]\ntg803521/radical.pilot.sandbox/ve_stampede_experiments/lib/python2.7/lib-old', '/work/01083/tg803521/radical.pilot.sandbox/ve_stampede_experiments/lib/python2.7/lib-dynload', '/opt/apps/intel13/python/2.7.9/lib/python2.7', '/opt/apps/intel13/python/2.7.9/lib/python2.7/plat-linux2', '/opt/apps/intel13/python/2.7.9/lib/python2.7/lib-tk']\npython: 2.7.9 (default, Apr 26 2015, 12:52:46) \n[GCC Intel(R) C++ gcc 4.4 mode]\nutils : 0.28  : /work/01083/tg803521/radical.pilot.sandbox/ve_stampede_experiments/rp_install/lib/python2.7/site-packages/radical/utils/__init__.pyc\nsaga  : v0.28-16-gd61cef7@devel : /work/01083/tg803521/radical.pilot.sandbox/ve_stampede_experiments/rp_install/lib/python2.7/site-packages/saga/__init__.pyc\npilot : v0.33-145-g688f18c@test-tmp_exec_dir : /work/01083/tg803521/radical.pilot.sandbox/ve_stampede_experiments/rp_install/lib/python2.7/site-packages/radical/pilot/__init__.pyc\n        type  : multicore\n        gitid : $Id$\n\n---------------------------------------------------------------------\n\n", 
            "submitted": 1435345582.227, 
            "unit_ids": [
                "unit.000000"
            ], 
            "unitmanager": "558da2ae23769c03ca887b48"
        }
    ], 
    "pmgr": [
        {
            "_id": "558da2ab23769c03ca887b47", 
            "data": {}, 
            "pilot_launcher_workers": 1
        }
    ], 
    "session": {
        "_id": "rp.session.ip-10-184-31-85.merzky.016612.0019", 
        "connected": 1435345579.211, 
        "created": 1435345579.211, 
        "name": "rp.session.ip-10-184-31-85.merzky.016612.0019"
    }, 
    "umgr": [
        {
            "_id": "558da2ae23769c03ca887b48", 
            "input_transfer_workers": 2, 
            "output_transfer_workers": 2, 
            "scheduler": "round_robin"
        }
    ], 
    "unit": [
        {
            "Agent_Input_Directives": [], 
            "Agent_Input_Status": null, 
            "Agent_Output_Directives": [], 
            "Agent_Output_Status": null, 
            "FTW_Input_Directives": [
                {
                    "action": "Transfer", 
                    "flags": [
                        "CreateParents", 
                        "SkipFailed"
                    ], 
                    "priority": 0, 
                    "source": "/tmp/input_1.dat", 
                    "state": "Done", 
                    "target": "input_1.dat"
                }
            ], 
            "FTW_Input_Status": "Done", 
            "FTW_Output_Directives": [
                {
                    "action": "Transfer", 
                    "flags": [
                        "CreateParents", 
                        "SkipFailed"
                    ], 
                    "priority": 0, 
                    "source": "input_1.dat", 
                    "state": "Done", 
                    "target": "input_1.dat"
                }
            ], 
            "FTW_Output_Status": "Done", 
            "_id": "unit.000000", 
            "callbackhistory": [
                {
                    "state": "StagingInput", 
                    "timestamp": 1435345583.266
                }, 
                {
                    "state": "PendingExecution", 
                    "timestamp": 1435345591.285
                }, 
                {
                    "state": "Allocating", 
                    "timestamp": 1435345712.581
                }, 
                {
                    "state": "StagingOutput", 
                    "timestamp": 1435345713.585
                }, 
                {
                    "state": "Done", 
                    "timestamp": 1435345715.591
                }
            ], 
            "description": {
                "arguments": [
                    "0"
                ], 
                "cleanup": false, 
                "cores": 1, 
                "environment": null, 
                "executable": "/bin/sleep", 
                "input_staging": [
                    {
                        "action": "Transfer", 
                        "flags": [
                            "CreateParents", 
                            "SkipFailed"
                        ], 
                        "priority": 0, 
                        "source": "/tmp/input_1.dat", 
                        "target": "input_1.dat"
                    }
                ], 
                "kernel": null, 
                "mpi": false, 
                "name": null, 
                "output_staging": [
                    {
                        "action": "Transfer", 
                        "flags": [
                            "CreateParents", 
                            "SkipFailed"
                        ], 
                        "priority": 0, 
                        "source": "input_1.dat", 
                        "target": "input_1.dat"
                    }
                ], 
                "post_exec": null, 
                "pre_exec": null, 
                "restartable": false, 
                "stderr": null, 
                "stdout": null
            }, 
            "exec_locs": null, 
            "exit_code": 0, 
            "finished": 1435345712.509, 
            "log": [
                {
                    "message": "Scheduled for data transfer to ComputePilot pilot.0000.", 
                    "timestamp": 1435345582.313
                }, 
                {
                    "message": "Transferring input file file://localhost//tmp/input_1.dat -> sftp://stampede.tacc.utexas.edu/work/01083/tg803521/radical.pilot.sandbox/rp.session.ip-10-184-31-85.merzky.016612.0019-pilot.0000//unit.000000/input_1.dat", 
                    "timestamp": 1435345590.614
                }, 
                {
                    "message": "All FTW Input Staging Directives done - 1.", 
                    "timestamp": 1435345590.617
                }, 
                {
                    "message": "unit needs no input staging", 
                    "timestamp": 1435345712.376
                }, 
                {
                    "message": "unit execution start", 
                    "timestamp": 1435345712.474
                }, 
                {
                    "message": "unit execution completed", 
                    "timestamp": 1435345712.51
                }, 
                {
                    "message": "FTW output staging needed", 
                    "timestamp": 1435345712.514
                }, 
                {
                    "message": "Starting transfer of input_1.dat", 
                    "timestamp": 1435345713.586
                }, 
                {
                    "message": "Transferring output file sftp://stampede.tacc.utexas.edu/work/01083/tg803521/radical.pilot.sandbox/rp.session.ip-10-184-31-85.merzky.016612.0019-pilot.0000//unit.000000/input_1.dat -> file://localhost/experiments/merzky/rp-paper-2015-micro/input_1.dat", 
                    "timestamp": 1435345714.49
                }, 
                {
                    "message": "All FTW output staging directives done - 1.", 
                    "timestamp": 1435345714.805
                }
            ], 
            "pilot": "pilot.0000", 
            "pilot_sandbox": "sftp://stampede.tacc.utexas.edu/work/01083/tg803521/radical.pilot.sandbox/rp.session.ip-10-184-31-85.merzky.016612.0019-pilot.0000/", 
            "restartable": false, 
            "sandbox": "sftp://stampede.tacc.utexas.edu/work/01083/tg803521/radical.pilot.sandbox/rp.session.ip-10-184-31-85.merzky.016612.0019-pilot.0000//unit.000000", 
            "slots": [
                "c560-401:0"
            ], 
            "started": 1435345712.474, 
            "state": "Done", 
            "statehistory": [
                {
                    "state": "Scheduling", 
                    "timestamp": 1435345582.299
                }, 
                {
                    "state": "StagingInput", 
                    "timestamp": 1435345583.247
                }, 
                {
                    "state": "PendingExecution", 
                    "timestamp": 1435345590.618
                }, 
                {
                    "state": "Allocating", 
                    "timestamp": 1435345712.284
                }, 
                {
                    "state": "Allocating", 
                    "timestamp": 1435345712.376
                }, 
                {
                    "state": "Executing", 
                    "timestamp": 1435345712.474
                }, 
                {
                    "state": "StagingOutput", 
                    "timestamp": 1435345712.51
                }, 
                {
                    "state": "StagingOutput", 
                    "timestamp": 1435345713.582
                }, 
                {
                    "state": "Done", 
                    "timestamp": 1435345714.806
                }
            ], 
            "stderr": "", 
            "stdout": "", 
            "submitted": 1435345582.301, 
            "unitmanager": "558da2ae23769c03ca887b48"
        }
    ]
}